swear_provention/__init__.py
swear_provention/swear_provention.py
swear_provention-0.0.7.dist-info/LICENSE
swear_provention-0.0.7.dist-info/METADATA
swear_provention-0.0.7.dist-info/WHEEL
swear_provention-0.0.7.dist-info/top_level.txt
swear_provention-0.0.7.dist-info/RECORD
